telegraph/__init__.py
telegraph/async_client.py
telegraph/client.py
telegraph/errors.py
telegraph/export.py
telegraph/templates.py
telegraph/types.py
telegraph/utils.py
telegraph_api_py-1.2.0.dist-info/licenses/LICENSE
telegraph_api_py-1.2.0.dist-info/METADATA
telegraph_api_py-1.2.0.dist-info/WHEEL
telegraph_api_py-1.2.0.dist-info/top_level.txt
telegraph_api_py-1.2.0.dist-info/RECORD
