Metadata-Version: 2.4
Name: telegraph-api-py
Version: 1.2.0
Summary: A complete Python wrapper for the Telegraph API
Author: Telegraph Python Contributors
Maintainer: Telegraph Python Contributors
License: MIT
Project-URL: Homepage, https://github.com/NehoraiHadad/telegraph-py
Project-URL: Documentation, https://github.com/NehoraiHadad/telegraph-py#readme
Project-URL: Repository, https://github.com/NehoraiHadad/telegraph-py
Project-URL: Bug Tracker, https://github.com/NehoraiHadad/telegraph-py/issues
Project-URL: Changelog, https://github.com/NehoraiHadad/telegraph-py/releases
Keywords: telegraph,telegraph-api,telegra.ph,api,wrapper,client,publishing,blogging
Classifier: Development Status :: 5 - Production/Stable
Classifier: Intended Audience :: Developers
Classifier: License :: OSI Approved :: MIT License
Classifier: Operating System :: OS Independent
Classifier: Programming Language :: Python
Classifier: Programming Language :: Python :: 3
Classifier: Programming Language :: Python :: 3.9
Classifier: Programming Language :: Python :: 3.10
Classifier: Programming Language :: Python :: 3.11
Classifier: Programming Language :: Python :: 3.12
Classifier: Programming Language :: Python :: 3.13
Classifier: Programming Language :: Python :: Implementation :: CPython
Classifier: Programming Language :: Python :: Implementation :: PyPy
Classifier: Topic :: Internet
Classifier: Topic :: Software Development :: Libraries
Classifier: Topic :: Software Development :: Libraries :: Python Modules
Classifier: Typing :: Typed
Requires-Python: >=3.9
License-File: LICENSE
Requires-Dist: requests>=2.25.0
Provides-Extra: async
Requires-Dist: aiohttp>=3.8.0; extra == "async"
Provides-Extra: dev
Requires-Dist: pytest>=7.0.0; extra == "dev"
Requires-Dist: pytest-asyncio>=0.21.0; extra == "dev"
Requires-Dist: pytest-cov>=4.0.0; extra == "dev"
Requires-Dist: black>=23.0.0; extra == "dev"
Requires-Dist: mypy>=1.0.0; extra == "dev"
Requires-Dist: ruff>=0.1.0; extra == "dev"
Provides-Extra: all
Requires-Dist: telegraph-api-py[async,dev]; extra == "all"
Dynamic: license-file
